zhkj_core/__init__.py
zhkj_core/bt_api.py
zhkj_core/common.py
zhkj_core/config.py
zhkj_core/constants.py
zhkj_core/ffmpeg_utils.py
zhkj_core/http_utils.py
zhkj_core/logger.py
zhkj_core/progress_util.py
zhkj_core/settings.py
zhkj_core/temp_file_manager.py
zhkj_core/timing_instrumentation.py
zhkj_core/video_util.py
zhkj_core/wrap/__init__.py
zhkj_core/wrap/_debounce.py
zhkj_core/wrap/_mutex_method.py
zhkj_core/wrap/_singleton.py
zhkj_core-0.1.1.dist-info/METADATA
zhkj_core-0.1.1.dist-info/WHEEL
zhkj_core-0.1.1.dist-info/top_level.txt
zhkj_core-0.1.1.dist-info/RECORD
