Metadata-Version: 2.4
Name: zhkj-core
Version: 0.1.1
Summary: ZHKJ common utilities library
Requires-Python: >=3.9
Requires-Dist: aiofile>=3.9.0
Requires-Dist: aiohttp>=3.13.2
Requires-Dist: pydantic==2.7.1
Requires-Dist: pydantic-settings==2.7.1
Requires-Dist: pyyaml>=6.0.3
Provides-Extra: http
Requires-Dist: aiohttp>=3.13.2; extra == "http"
Requires-Dist: requests>=2.32.5; extra == "http"
Provides-Extra: logging
Requires-Dist: loguru>=0.7.3; extra == "logging"
Provides-Extra: all
Requires-Dist: aiohttp>=3.13.2; extra == "all"
Requires-Dist: loguru>=0.7.3; extra == "all"
Requires-Dist: pydantic==2.7.1; extra == "all"
Requires-Dist: pydantic-settings==2.7.1; extra == "all"
Requires-Dist: pyyaml>=6.0.3; extra == "all"
Requires-Dist: requests>=2.32.5; extra == "all"
